vxpy/__init__.py
vxpy/__main__.py
vxpy/calib.py
vxpy/config.py
vxpy/definitions.py
vxpy/vxpy_icon.png
vxpy/vxpy_icon.svg
vxpy/api/__init__.py
vxpy/api/attribute.py
vxpy/api/event.py
vxpy/api/protocol.py
vxpy/api/routine.py
vxpy/api/visual.py
vxpy/calibration/__init__.py
vxpy/calibration/calib_manager/__init__.py
vxpy/calibration/calib_manager/calib_manager.py
vxpy/calibration/calib_manager/calib_manager_spherical_4_channel_projection.py
vxpy/calibration/calib_manager/calibration_utils.py
vxpy/configuration/__init__.py
vxpy/configuration/config_manager/__init__.py
vxpy/configuration/config_manager/config_manager.py
vxpy/configuration/config_manager/config_manager_cameras.py
vxpy/configuration/config_manager/config_manager_display.py
vxpy/configuration/config_manager/config_manager_routines.py
vxpy/core/__init__.py
vxpy/core/attribute.py
vxpy/core/container.py
vxpy/core/control.py
vxpy/core/dependency.py
vxpy/core/event.py
vxpy/core/io.py
vxpy/core/ipc.py
vxpy/core/logger.py
vxpy/core/process.py
vxpy/core/protocol.py
vxpy/core/routine.py
vxpy/core/setup.py
vxpy/core/transform.py
vxpy/core/ui.py
vxpy/core/visual.py
vxpy/core/devices/__init__.py
vxpy/core/devices/camera.py
vxpy/core/devices/serial.py
vxpy/devices/__init__.py
vxpy/devices/arduino_daq.py
vxpy/devices/lightcrafter.py
vxpy/devices/telemetrix_device.py
vxpy/devices/virtual_daq.py
vxpy/devices/camera/__init__.py
vxpy/devices/camera/basler_pylon.py
vxpy/devices/camera/tis_linux_gst.py
vxpy/devices/camera/tis_windows_tisgrabber.py
vxpy/devices/camera/virtual_camera.py
vxpy/ext_lib/lightcrafter/README.md
vxpy/ext_lib/lightcrafter/lightcrafter_interface.py
vxpy/ext_lib/tis_windows/README.md
vxpy/ext_lib/tis_windows/TIS_UDSHL11.dll
vxpy/ext_lib/tis_windows/TIS_UDSHL11_x64.dll
vxpy/ext_lib/tis_windows/__init__.py
vxpy/ext_lib/tis_windows/tisgrabber.dll
vxpy/ext_lib/tis_windows/tisgrabber.py
vxpy/ext_lib/tis_windows/tisgrabber_x64.dll
vxpy/extras/__init__.py
vxpy/extras/ca_processing.py
vxpy-0.1.6.dist-info/LICENSE
vxpy-0.1.6.dist-info/METADATA
vxpy-0.1.6.dist-info/WHEEL
vxpy-0.1.6.dist-info/entry_points.txt
vxpy-0.1.6.dist-info/top_level.txt
vxpy-0.1.6.dist-info/RECORD
