Metadata-Version: 2.1
Name: vxpy
Version: 0.1.6
Summary: vxPy - Vision experiments in Python
Author-email: Tim Hladnik <contact@vxpy.org>
License: GNU GENERAL PUBLIC LICENSE
Project-URL: Homepage, https://github.com/thladnik/vxpy
Keywords: neuroscience,experiment,visual stimulation,behavioral tracking
Classifier: Development Status :: 3 - Alpha
Classifier: Intended Audience :: Science/Research
Classifier: License :: OSI Approved :: GNU General Public License v3 (GPLv3)
Classifier: Operating System :: POSIX :: Linux
Classifier: Operating System :: Microsoft :: Windows
Classifier: Operating System :: Microsoft :: Windows :: Windows 11
Classifier: Programming Language :: Python
Classifier: Programming Language :: Python :: 3.8
Classifier: Programming Language :: Python :: 3.9
Classifier: Programming Language :: Python :: 3.10
Classifier: Programming Language :: Python :: 3.11
Classifier: Topic :: Scientific/Engineering
Requires-Python: >=3.8
License-File: LICENSE
Requires-Dist: deprecation >=2.1.0
Requires-Dist: ffmpeg-python >=0.2.0
Requires-Dist: gitpython >=3.1.31
Requires-Dist: glfw >=2.5.5
Requires-Dist: h5py >=3.7.0
Requires-Dist: matplotlib >=3.7.2
Requires-Dist: numpy >=1.23.4
Requires-Dist: opencv-python-headless >=4.6.0.66
Requires-Dist: pyFirmata >=1.1.0
Requires-Dist: pyqtdarktheme >=2.1.0
Requires-Dist: pyqtgraph >=0.13.1
Requires-Dist: pyyaml >=6.0
Requires-Dist: PySide6 <6.5.0,>=6.4.0
Requires-Dist: requests >=2.28.1
Requires-Dist: scipy >=1.9.2
Requires-Dist: setuptools >=65.5.0
Requires-Dist: vispy >=0.11.0
Requires-Dist: tomli ; python_version <= "3.11"
Provides-Extra: dev
Requires-Dist: pip-tools ; extra == 'dev'
Requires-Dist: pytest ; extra == 'dev'
Requires-Dist: build ; extra == 'dev'
Requires-Dist: twine ; extra == 'dev'
